plover_startup_py/__init__.py
plover_startup_py-0.2.0.dist-info/LICENSE
plover_startup_py-0.2.0.dist-info/METADATA
plover_startup_py-0.2.0.dist-info/WHEEL
plover_startup_py-0.2.0.dist-info/entry_points.txt
plover_startup_py-0.2.0.dist-info/top_level.txt
plover_startup_py-0.2.0.dist-info/zip-safe
plover_startup_py-0.2.0.dist-info/RECORD
