Metadata-Version: 2.1
Name: plover-startup-py
Version: 0.2.0
Summary: Quick and dirty plugin to run something when Plover starts.
Home-page: https://github.com/user202729/plover-startup-py
Author: user202729
License: GNU General Public License v3 or later (GPLv3+)
Keywords: plover plover_plugin
Platform: UNKNOWN
Classifier: Environment :: Plugins
Classifier: License :: OSI Approved :: GNU General Public License v3 or later (GPLv3+)
Classifier: Operating System :: OS Independent
Classifier: Programming Language :: Python :: 3
Requires-Dist: plover (>=4.0.0.dev8)
